client/__init__.py
client/pofile.py
tests/__init__.py
tests/test_api_urls.py
tests/test_find.py
tests/test_validation.py
pofile_cli-0.1.0.dist-info/LICENSE
pofile_cli-0.1.0.dist-info/METADATA
pofile_cli-0.1.0.dist-info/WHEEL
pofile_cli-0.1.0.dist-info/entry_points.txt
pofile_cli-0.1.0.dist-info/top_level.txt
pofile_cli-0.1.0.dist-info/RECORD
