Metadata-Version: 2.1
Name: pofile-cli
Version: 0.1.0
Summary: A CLI tool to translate PO files using https://pofile.io/.
Home-page: https://github.com/terrefta/pofile-cli
Author: Terrefta AB
Author-email: kontakt@terrefta.se
License: MIT
Classifier: Programming Language :: Python :: 3
Classifier: License :: OSI Approved :: MIT License
Classifier: Operating System :: OS Independent
Requires-Python: >=3.6
License-File: LICENSE
Requires-Dist: requests>=2.0.0
Requires-Dist: polib>=1.0.0
Provides-Extra: dev
Requires-Dist: pytest; extra == "dev"
